geomaroc/__init__.py
geomaroc/geo.py
geomaroc/utils.py
geomaroc/data/Maroc.json
geomaroc/data/__init__.py
geomaroc/data/prov_id.json
geomaroc/data/prov_region.json
geomaroc/data/region_id.json
geomaroc/data/region_prov.json
geomaroc/data/Beni-Mellal-Khenifra/Azilal.json
geomaroc/data/Beni-Mellal-Khenifra/Beni-Mellal.json
geomaroc/data/Beni-Mellal-Khenifra/Fquih-Ben-Salah.json
geomaroc/data/Beni-Mellal-Khenifra/Khenifra.json
geomaroc/data/Beni-Mellal-Khenifra/Khouribga.json
geomaroc/data/Beni-Mellal-Khenifra/__init__.py
geomaroc/data/Casablanca-Settat/Benslimane.json
geomaroc/data/Casablanca-Settat/Berrechid.json
geomaroc/data/Casablanca-Settat/Casablanca.json
geomaroc/data/Casablanca-Settat/El-Jadida.json
geomaroc/data/Casablanca-Settat/Mediouna.json
geomaroc/data/Casablanca-Settat/Mohammadia.json
geomaroc/data/Casablanca-Settat/Nouaceur.json
geomaroc/data/Casablanca-Settat/Settat.json
geomaroc/data/Casablanca-Settat/Sidi-Bennour.json
geomaroc/data/Casablanca-Settat/__init__.py
geomaroc/data/Draa-Tafilalet/Errachidia.json
geomaroc/data/Draa-Tafilalet/Midelt.json
geomaroc/data/Draa-Tafilalet/Ouarzazate.json
geomaroc/data/Draa-Tafilalet/Tinghir.json
geomaroc/data/Draa-Tafilalet/Zagora.json
geomaroc/data/Draa-Tafilalet/__init__.py
geomaroc/data/Eddakhla-Oued-Eddahab/Aousserd.json
geomaroc/data/Eddakhla-Oued-Eddahab/Oued-Ed-Dahab.json
geomaroc/data/Eddakhla-Oued-Eddahab/__init__.py
geomaroc/data/Fes-Meknes/Boulemane.json
geomaroc/data/Fes-Meknes/El-Hajeb.json
geomaroc/data/Fes-Meknes/Fes.json
geomaroc/data/Fes-Meknes/Ifrane.json
geomaroc/data/Fes-Meknes/Meknes.json
geomaroc/data/Fes-Meknes/Moulay-Yacoub.json
geomaroc/data/Fes-Meknes/Sefrou.json
geomaroc/data/Fes-Meknes/Taounate.json
geomaroc/data/Fes-Meknes/Taza.json
geomaroc/data/Fes-Meknes/__init__.py
geomaroc/data/Guelmim-Oued-Noun/Assa-Zag.json
geomaroc/data/Guelmim-Oued-Noun/Guelmim.json
geomaroc/data/Guelmim-Oued-Noun/Sidi-Ifni.json
geomaroc/data/Guelmim-Oued-Noun/Tan-Tan.json
geomaroc-1.0.3.dist-info/LICENSE.txt
geomaroc-1.0.3.dist-info/METADATA
geomaroc-1.0.3.dist-info/WHEEL
geomaroc-1.0.3.dist-info/top_level.txt
geomaroc-1.0.3.dist-info/RECORD
