Metadata-Version: 2.1
Name: geomaroc
Version: 1.0.3
Summary: A Python library to easily visualize geospatial data of Morocco.
Home-page: https://github.com/AmineAndam04/geomaroc
Author: ANDAM Amine
Author-email: andamamine83@gmail.com
Keywords: geospatial,data visualization,Morocco,data-science,maps
Classifier: Programming Language :: Python :: 3
Classifier: License :: OSI Approved :: MIT License
Classifier: Operating System :: OS Independent
Requires-Python: >=3.6
License-File: LICENSE.txt
